Best_Lib/Best_lib_func.py
Best_Lib/__init__.py
Best_Lib-0.0.1.dist-info/METADATA
Best_Lib-0.0.1.dist-info/WHEEL
Best_Lib-0.0.1.dist-info/top_level.txt
Best_Lib-0.0.1.dist-info/RECORD
