Metadata-Version: 2.1
Name: Best-Lib
Version: 0.0.1
Summary: Old but Gold
Home-page: https://github.com/Lenapavlova/Best_Lib
Author: Lenapavlova
Author-email: lena.pavlova.9797@mail.ru
Project-URL: GitHub, https://github.com/Lenapavlova/Best_Lib
Keywords: fun
Classifier: Programming Language :: Python :: 3.11
Classifier: License :: OSI Approved :: MIT License
Classifier: Operating System :: OS Independent
Requires-Python: >=3.6
